st_aggrid/__init__.py
st_aggrid/_version.py
st_aggrid/grid_options_builder.py
st_aggrid/shared.py
st_aggrid/frontend/build/asset-manifest.json
st_aggrid/frontend/build/bootstrap.min.css
st_aggrid/frontend/build/bootstrap.min.css.map
st_aggrid/frontend/build/index.html
st_aggrid/frontend/build/static/css/main.542a1263.css
st_aggrid/frontend/build/static/css/main.542a1263.css.map
st_aggrid/frontend/build/static/js/main.c98834ed.js
st_aggrid/frontend/build/static/js/main.c98834ed.js.LICENSE.txt
st_aggrid/frontend/build/static/js/main.c98834ed.js.map
st_aggrid/frontend/build/static/media/source-sans-pro-all-400-normal.1882629b5eaf2ec74fbf.woff
st_aggrid/frontend/build/static/media/source-sans-pro-cyrillic-400-normal.d1cfd8b7bb2cbe3fabb0.woff2
st_aggrid/frontend/build/static/media/source-sans-pro-cyrillic-ext-400-normal.de95c5209ef26bf69ccf.woff2
st_aggrid/frontend/build/static/media/source-sans-pro-greek-400-normal.9c7d72dcc7a044db07b1.woff2
st_aggrid/frontend/build/static/media/source-sans-pro-greek-ext-400-normal.1b1cb10170f2616853f0.woff2
st_aggrid/frontend/build/static/media/source-sans-pro-latin-400-normal.c0d191aa7fb798623030.woff2
st_aggrid/frontend/build/static/media/source-sans-pro-latin-ext-400-normal.fbd4fe33a443c83e04f1.woff2
st_aggrid/frontend/build/static/media/source-sans-pro-vietnamese-400-normal.e84a4369ad213f658ebb.woff2
streamlit_jdgrid-0.3.7.dist-info/LICENSE
streamlit_jdgrid-0.3.7.dist-info/METADATA
streamlit_jdgrid-0.3.7.dist-info/WHEEL
streamlit_jdgrid-0.3.7.dist-info/top_level.txt
streamlit_jdgrid-0.3.7.dist-info/RECORD
