Metadata-Version: 2.1
Name: streamlit-jdgrid
Version: 0.3.7
Summary: Streamlit component implementation of ag-grid
Author-email: Pablo Fonseca <pablo.fonseca+pip@gmail.com>, Jake Diamond <dubbul@protonmail.com>
Classifier: Programming Language :: Python :: 3
Classifier: License :: OSI Approved :: MIT License
Classifier: Operating System :: OS Independent
Requires-Python: >=3.9
License-File: LICENSE
Requires-Dist: numpy
Requires-Dist: pandas >=1.2
Requires-Dist: python-decouple >=3.6
Requires-Dist: simplejson >=3.0
Requires-Dist: streamlit >=0.87.0
Provides-Extra: dev
Requires-Dist: black ; extra == 'dev'
Requires-Dist: build ; extra == 'dev'
Requires-Dist: ruff ; extra == 'dev'
Requires-Dist: sphinx ; extra == 'dev'
Requires-Dist: watchdog <3.0.0,>=2.1.9 ; extra == 'dev'
